opal_trino_fetcher/__init__.py
opal_trino_fetcher/provider.py
opal_trino_fetcher-0.0.5.dist-info/METADATA
opal_trino_fetcher-0.0.5.dist-info/WHEEL
opal_trino_fetcher-0.0.5.dist-info/top_level.txt
opal_trino_fetcher-0.0.5.dist-info/RECORD
